torque_utils/__init__.py
torque_utils/plot.py
torque_utils/sigproc.py
torque_utils/statscalc.py
torque_utils/vidproc.py
torque_utils-0.0.8.dist-info/LICENSE.txt
torque_utils-0.0.8.dist-info/METADATA
torque_utils-0.0.8.dist-info/WHEEL
torque_utils-0.0.8.dist-info/top_level.txt
torque_utils-0.0.8.dist-info/RECORD
